spgraph_client/__init__.py
spgraph_client/client.py
spgraph_client-0.1.0.dist-info/licenses/LICENSE
spgraph_client-0.1.0.dist-info/METADATA
spgraph_client-0.1.0.dist-info/WHEEL
spgraph_client-0.1.0.dist-info/top_level.txt
spgraph_client-0.1.0.dist-info/RECORD
