Metadata-Version: 2.4
Name: spgraph-client
Version: 0.1.0
Summary: A Python client for performing SharePoint actions via Microsoft Graph API.
Author-email: Harry Dinh <hoangdinh.2710@gmail.com>
License: MIT
Project-URL: Homepage, https://github.com/hoangdinh2710/spgraph-client
Requires-Python: >=3.8
License-File: LICENSE
Requires-Dist: requests
Requires-Dist: pandas
Dynamic: license-file
